README.md
setup.cfg
setup.py
distributions/Binomialdistribution.py
distributions/Gaussiandistribution.py
distributions/Generaldistribution.py
distributions/__init__.py
rck_distributions.egg-info/PKG-INFO
rck_distributions.egg-info/SOURCES.txt
rck_distributions.egg-info/dependency_links.txt
rck_distributions.egg-info/not-zip-safe
rck_distributions.egg-info/top_level.txt